tests/__init__.py
tests/test_bitcoin_clients.py
tests/test_bitcoin_utils.py
xchainpy_bitcoin/__init__.py
xchainpy_bitcoin/blockstream_api.py
xchainpy_bitcoin/client.py
xchainpy_bitcoin/const.py
xchainpy_bitcoin/crypto.py
xchainpy_bitcoin/haskoin_api.py
xchainpy_bitcoin/sochain_api.py
xchainpy_bitcoin/utils.py
xchainpy_bitcoin/models/__init__.py
xchainpy_bitcoin/models/client_types.py
xchainpy_bitcoin/models/common.py
xchainpy_bitcoin-0.2.3.dist-info/LICENSE
xchainpy_bitcoin-0.2.3.dist-info/METADATA
xchainpy_bitcoin-0.2.3.dist-info/WHEEL
xchainpy_bitcoin-0.2.3.dist-info/top_level.txt
xchainpy_bitcoin-0.2.3.dist-info/RECORD
